{
  "postgresql": {
    "contrib": {
      "extensions": [
        "plpgsql"
      ],
      "packages": [
        "postgresql-contrib-9.3"
      ]
    },
    "password": {
      "postgres": "dce2f13b5c9349d9cfe21ca6f8b278fc"
    },
    "server": {
      "packages": [
        "postgresql-9.3"
      ]
    },
    "client": {
      "packages": [
        "postgresql-client-9.3",
        "libpq-dev"
      ]
    },
    "dir" : "/etc/postgresql/9.3/main",
    "service_name" : "postgresql",
    "setup_script" : "postgresql93-setup",
    "enable_pgdg_apt": true,
    "version": "9.3"
  },
  "rbenv": {
    "user_installs": [{
      "user": "vagrant",
      "rubies": ["2.2.4"],
      "global": "2.2.4",
      "local": "2.2.4",
      "gems": {
        "2.2.4": [
          {
            "name": "bundler"
          },
          {
            "name": "mailcatcher"
          }
        ]
      }
    }]
  }
}
